[{"id":2260535,"name":"Brazzaville","timezone":{"dstOffset":1,"gmtOffset":1,"timeZoneId":"Africa/Brazzaville"},"lat":-4.26613,"lng":15.28318,"population":1284609},{"id":2255414,"name":"Pointe-Noire","timezone":{"dstOffset":1,"gmtOffset":1,"timeZoneId":"Africa/Brazzaville"},"lat":-4.77609,"lng":11.86352,"population":659084},{"id":2258261,"name":"Dolisie","timezone":{"dstOffset":1,"gmtOffset":1,"timeZoneId":"Africa/Brazzaville"},"lat":-4.19834,"lng":12.66664,"population":103894},{"id":2259383,"name":"Kayes","timezone":{"dstOffset":1,"gmtOffset":1,"timeZoneId":"Africa/Brazzaville"},"lat":-4.20493,"lng":13.28608,"population":58737},{"id":2255542,"name":"Owando","timezone":{"dstOffset":1,"gmtOffset":1,"timeZoneId":"Africa/Brazzaville"},"lat":-0.48193,"lng":15.89988,"population":23952},{"id":2255564,"name":"Ouésso","timezone":{"dstOffset":1,"gmtOffset":1,"timeZoneId":"Africa/Brazzaville"},"lat":1.61361,"lng":16.05167,"population":23915},{"id":2258378,"name":"Loandjili","timezone":{"dstOffset":1,"gmtOffset":1,"timeZoneId":"Africa/Brazzaville"},"lat":-4.75611,"lng":11.85778,"population":23204},{"id":2257990,"name":"Madingou","timezone":{"dstOffset":1,"gmtOffset":1,"timeZoneId":"Africa/Brazzaville"},"lat":-4.15361,"lng":13.55,"population":22760},{"id":2259947,"name":"Gamboma","timezone":{"dstOffset":1,"gmtOffset":1,"timeZoneId":"Africa/Brazzaville"},"lat":-1.87639,"lng":15.86444,"population":20877},{"id":2259655,"name":"Impfondo","timezone":{"dstOffset":1,"gmtOffset":1,"timeZoneId":"Africa/Brazzaville"},"lat":1.61804,"lng":18.05981,"population":20859},{"id":2255285,"name":"Sibiti","timezone":{"dstOffset":1,"gmtOffset":1,"timeZoneId":"Africa/Brazzaville"},"lat":-3.68192,"lng":13.34985,"population":19089},{"id":2256895,"name":"Mossendjo","timezone":{"dstOffset":1,"gmtOffset":1,"timeZoneId":"Africa/Brazzaville"},"lat":-2.94968,"lng":12.70423,"population":18231},{"id":2258984,"name":"Kinkala","timezone":{"dstOffset":1,"gmtOffset":1,"timeZoneId":"Africa/Brazzaville"},"lat":-4.36139,"lng":14.76444,"population":13882},{"id":2257879,"name":"Makoua","timezone":{"dstOffset":1,"gmtOffset":1,"timeZoneId":"Africa/Brazzaville"},"lat":0.00694,"lng":15.63333,"population":11355},{"id":2260401,"name":"Djambala","timezone":{"dstOffset":1,"gmtOffset":1,"timeZoneId":"Africa/Brazzaville"},"lat":-2.54472,"lng":14.75333,"population":9650},{"id":2260009,"name":"Ewo","timezone":{"dstOffset":1,"gmtOffset":1,"timeZoneId":"Africa/Brazzaville"},"lat":-0.8725,"lng":14.82056,"population":4923},{"id":2255304,"name":"Sémbé","timezone":{"dstOffset":1,"gmtOffset":1,"timeZoneId":"Africa/Brazzaville"},"lat":1.64806,"lng":14.58056,"population":3113},{"id":2258375,"name":"Loango","timezone":{"dstOffset":1,"gmtOffset":1,"timeZoneId":"Africa/Brazzaville"},"lat":-4.65194,"lng":11.8125,"population":0},{"id":8521334,"name":"Nkayi","timezone":{"dstOffset":1,"gmtOffset":1,"timeZoneId":"Africa/Brazzaville"},"lat":-4.18396,"lng":13.2859,"population":0}]