[{"id":2964574,"name":"Dublin","timezone":{"dstOffset":1,"gmtOffset":0,"timeZoneId":"Europe/Dublin"},"lat":53.33306,"lng":-6.24889,"population":1024027},{"id":2965140,"name":"Cork","timezone":{"dstOffset":1,"gmtOffset":0,"timeZoneId":"Europe/Dublin"},"lat":51.89797,"lng":-8.47061,"population":190384},{"id":2964506,"name":"Dún Laoghaire","timezone":{"dstOffset":1,"gmtOffset":0,"timeZoneId":"Europe/Dublin"},"lat":53.29395,"lng":-6.13586,"population":185400},{"id":2962943,"name":"Limerick","timezone":{"dstOffset":1,"gmtOffset":0,"timeZoneId":"Europe/Dublin"},"lat":52.66472,"lng":-8.62306,"population":90054},{"id":2964180,"name":"Galway","timezone":{"dstOffset":1,"gmtOffset":0,"timeZoneId":"Europe/Dublin"},"lat":53.27194,"lng":-9.04889,"population":70686},{"id":2961284,"name":"Tallaght","timezone":{"dstOffset":1,"gmtOffset":0,"timeZoneId":"Europe/Dublin"},"lat":53.2859,"lng":-6.37344,"population":64282},{"id":2960992,"name":"Waterford","timezone":{"dstOffset":1,"gmtOffset":0,"timeZoneId":"Europe/Dublin"},"lat":52.25833,"lng":-7.11194,"population":47904},{"id":2961297,"name":"Swords","timezone":{"dstOffset":1,"gmtOffset":0,"timeZoneId":"Europe/Dublin"},"lat":53.45972,"lng":-6.21806,"population":36924},{"id":2964661,"name":"Drogheda","timezone":{"dstOffset":1,"gmtOffset":0,"timeZoneId":"Europe/Dublin"},"lat":53.71889,"lng":-6.34778,"population":33441},{"id":2964540,"name":"Dundalk","timezone":{"dstOffset":1,"gmtOffset":0,"timeZoneId":"Europe/Dublin"},"lat":54,"lng":-6.41667,"population":33428},{"id":2962308,"name":"Navan","timezone":{"dstOffset":1,"gmtOffset":0,"timeZoneId":"Europe/Dublin"},"lat":53.65278,"lng":-6.68139,"population":24545},{"id":2964405,"name":"Ennis","timezone":{"dstOffset":1,"gmtOffset":0,"timeZoneId":"Europe/Dublin"},"lat":52.84361,"lng":-8.98639,"population":24427},{"id":2966794,"name":"Balbriggan","timezone":{"dstOffset":1,"gmtOffset":0,"timeZoneId":"Europe/Dublin"},"lat":53.61278,"lng":-6.18194,"population":23364},{"id":2961123,"name":"Tralee","timezone":{"dstOffset":1,"gmtOffset":0,"timeZoneId":"Europe/Dublin"},"lat":52.27042,"lng":-9.70264,"population":22941},{"id":3315278,"name":"Sandyford","timezone":{"dstOffset":1,"gmtOffset":0,"timeZoneId":"Europe/Dublin"},"lat":53.2747,"lng":-6.2253,"population":22288},{"id":2963398,"name":"Kilkenny","timezone":{"dstOffset":1,"gmtOffset":0,"timeZoneId":"Europe/Dublin"},"lat":52.65417,"lng":-7.25222,"population":21589},{"id":2962334,"name":"Naas","timezone":{"dstOffset":1,"gmtOffset":0,"timeZoneId":"Europe/Dublin"},"lat":53.21583,"lng":-6.66694,"population":20713},{"id":2961423,"name":"Sligo","timezone":{"dstOffset":1,"gmtOffset":0,"timeZoneId":"Europe/Dublin"},"lat":54.26969,"lng":-8.46943,"population":20228},{"id":2965768,"name":"Carlow","timezone":{"dstOffset":1,"gmtOffset":0,"timeZoneId":"Europe/Dublin"},"lat":52.84083,"lng":-6.92611,"population":20055},{"id":2960964,"name":"Wexford","timezone":{"dstOffset":1,"gmtOffset":0,"timeZoneId":"Europe/Dublin"},"lat":52.33417,"lng":-6.4575,"population":19913},{"id":2964303,"name":"Finglas","timezone":{"dstOffset":1,"gmtOffset":0,"timeZoneId":"Europe/Dublin"},"lat":53.38917,"lng":-6.29694,"population":19768},{"id":2965529,"name":"Celbridge","timezone":{"dstOffset":1,"gmtOffset":0,"timeZoneId":"Europe/Dublin"},"lat":53.33861,"lng":-6.54361,"population":19537},{"id":2962290,"name":"Droichead Nua","timezone":{"dstOffset":1,"gmtOffset":0,"timeZoneId":"Europe/Dublin"},"lat":53.18194,"lng":-6.79667,"population":18860},{"id":2965353,"name":"Clonmel","timezone":{"dstOffset":1,"gmtOffset":0,"timeZoneId":"Europe/Dublin"},"lat":52.355,"lng":-7.70389,"population":17394},{"id":2962361,"name":"Mullingar","timezone":{"dstOffset":1,"gmtOffset":0,"timeZoneId":"Europe/Dublin"},"lat":53.53333,"lng":-7.35,"population":17262},{"id":2962961,"name":"Letterkenny","timezone":{"dstOffset":1,"gmtOffset":0,"timeZoneId":"Europe/Dublin"},"lat":54.95,"lng":-7.73333,"population":16901},{"id":2966110,"name":"Blanchardstown","timezone":{"dstOffset":1,"gmtOffset":0,"timeZoneId":"Europe/Dublin"},"lat":53.38806,"lng":-6.37556,"population":16511},{"id":2966839,"name":"Athlone","timezone":{"dstOffset":1,"gmtOffset":0,"timeZoneId":"Europe/Dublin"},"lat":53.43333,"lng":-7.95,"population":15951},{"id":2962725,"name":"Malahide","timezone":{"dstOffset":1,"gmtOffset":0,"timeZoneId":"Europe/Dublin"},"lat":53.45083,"lng":-6.15444,"population":15846},{"id":2962974,"name":"Leixlip","timezone":{"dstOffset":1,"gmtOffset":0,"timeZoneId":"Europe/Dublin"},"lat":53.36583,"lng":-6.49556,"population":15452},{"id":6691033,"name":"Donaghmede","timezone":{"dstOffset":1,"gmtOffset":0,"timeZoneId":"Europe/Dublin"},"lat":53.39845,"lng":-6.16179,"population":15299},{"id":2962785,"name":"Lucan","timezone":{"dstOffset":1,"gmtOffset":0,"timeZoneId":"Europe/Dublin"},"lat":53.35736,"lng":-6.44859,"population":15269},{"id":7870988,"name":"Kilquade","timezone":{"dstOffset":1,"gmtOffset":0,"timeZoneId":"Europe/Dublin"},"lat":53.09743,"lng":-6.08411,"population":14886},{"id":2965715,"name":"Carrigaline","timezone":{"dstOffset":1,"gmtOffset":0,"timeZoneId":"Europe/Dublin"},"lat":51.81167,"lng":-8.39861,"population":14775},{"id":7838921,"name":"Knocklyon","timezone":{"dstOffset":1,"gmtOffset":0,"timeZoneId":"Europe/Dublin"},"lat":53.2803,"lng":-6.3313,"population":14628},{"id":2965381,"name":"Clondalkin","timezone":{"dstOffset":1,"gmtOffset":0,"timeZoneId":"Europe/Dublin"},"lat":53.32444,"lng":-6.39722,"population":14508},{"id":2960936,"name":"Wicklow","timezone":{"dstOffset":1,"gmtOffset":0,"timeZoneId":"Europe/Dublin"},"lat":52.975,"lng":-6.04944,"population":14048},{"id":2962026,"name":"Portlaoise","timezone":{"dstOffset":1,"gmtOffset":0,"timeZoneId":"Europe/Dublin"},"lat":53.03441,"lng":-7.29979,"population":13622},{"id":2963848,"name":"Greystones","timezone":{"dstOffset":1,"gmtOffset":0,"timeZoneId":"Europe/Dublin"},"lat":53.14083,"lng":-6.06306,"population":13492},{"id":2965654,"name":"Castlebar","timezone":{"dstOffset":1,"gmtOffset":0,"timeZoneId":"Europe/Dublin"},"lat":53.85,"lng":-9.3,"population":12874},{"id":3315280,"name":"Foxrock","timezone":{"dstOffset":1,"gmtOffset":0,"timeZoneId":"Europe/Dublin"},"lat":53.26667,"lng":-6.17417,"population":12870},{"id":2966837,"name":"Athy","timezone":{"dstOffset":1,"gmtOffset":0,"timeZoneId":"Europe/Dublin"},"lat":52.99139,"lng":-6.98028,"population":12855},{"id":2962668,"name":"Maynooth","timezone":{"dstOffset":1,"gmtOffset":0,"timeZoneId":"Europe/Dublin"},"lat":53.385,"lng":-6.59361,"population":12510},{"id":2964532,"name":"Dundrum","timezone":{"dstOffset":1,"gmtOffset":0,"timeZoneId":"Europe/Dublin"},"lat":53.29067,"lng":-6.25714,"population":12152},{"id":2966883,"name":"Arklow","timezone":{"dstOffset":1,"gmtOffset":0,"timeZoneId":"Europe/Dublin"},"lat":52.79306,"lng":-6.14139,"population":11761},{"id":2961086,"name":"Tullamore","timezone":{"dstOffset":1,"gmtOffset":0,"timeZoneId":"Europe/Dublin"},"lat":53.27389,"lng":-7.48889,"population":11575},{"id":2966870,"name":"Ashbourne","timezone":{"dstOffset":1,"gmtOffset":0,"timeZoneId":"Europe/Dublin"},"lat":53.51163,"lng":-6.39821,"population":11355},{"id":2964963,"name":"Crumlin","timezone":{"dstOffset":1,"gmtOffset":0,"timeZoneId":"Europe/Dublin"},"lat":53.32417,"lng":-6.32861,"population":11294},{"id":2961896,"name":"Rathmines","timezone":{"dstOffset":1,"gmtOffset":0,"timeZoneId":"Europe/Dublin"},"lat":53.32028,"lng":-6.26333,"population":11044},{"id":2962696,"name":"Marino","timezone":{"dstOffset":1,"gmtOffset":0,"timeZoneId":"Europe/Dublin"},"lat":53.37022,"lng":-6.23646,"population":11023},{"id":2963007,"name":"Laytown","timezone":{"dstOffset":1,"gmtOffset":0,"timeZoneId":"Europe/Dublin"},"lat":53.68194,"lng":-6.23917,"population":10889},{"id":7869995,"name":"Jobstown","timezone":{"dstOffset":1,"gmtOffset":0,"timeZoneId":"Europe/Dublin"},"lat":53.27866,"lng":-6.40803,"population":10825},{"id":2964745,"name":"Donnybrook","timezone":{"dstOffset":1,"gmtOffset":0,"timeZoneId":"Europe/Dublin"},"lat":53.31375,"lng":-6.22274,"population":10645},{"id":2965260,"name":"Queenstown","timezone":{"dstOffset":1,"gmtOffset":0,"timeZoneId":"Europe/Dublin"},"lat":51.85722,"lng":-8.29917,"population":10501},{"id":2961523,"name":"Shankill","timezone":{"dstOffset":1,"gmtOffset":0,"timeZoneId":"Europe/Dublin"},"lat":53.22611,"lng":-6.12444,"population":10102},{"id":2966778,"name":"Ballina","timezone":{"dstOffset":1,"gmtOffset":0,"timeZoneId":"Europe/Dublin"},"lat":54.11667,"lng":-9.16667,"population":10087},{"id":2965882,"name":"Cabinteely","timezone":{"dstOffset":1,"gmtOffset":0,"timeZoneId":"Europe/Dublin"},"lat":53.26973,"lng":-6.16058,"population":10038},{"id":2964820,"name":"Derry","timezone":{"dstOffset":1,"gmtOffset":0,"timeZoneId":"Europe/Dublin"},"lat":51.58666,"lng":-9.05026,"population":10000},{"id":3315430,"name":"Oldbawn","timezone":{"dstOffset":1,"gmtOffset":0,"timeZoneId":"Europe/Dublin"},"lat":53.27556,"lng":-6.3675,"population":9784},{"id":2964403,"name":"Enniscorthy","timezone":{"dstOffset":1,"gmtOffset":0,"timeZoneId":"Europe/Dublin"},"lat":52.50083,"lng":-6.55778,"population":9709},{"id":3310247,"name":"Shannon","timezone":{"dstOffset":1,"gmtOffset":0,"timeZoneId":"Europe/Dublin"},"lat":52.70389,"lng":-8.86417,"population":9673},{"id":2961461,"name":"Skerries","timezone":{"dstOffset":1,"gmtOffset":0,"timeZoneId":"Europe/Dublin"},"lat":53.58278,"lng":-6.10833,"population":9671},{"id":2966670,"name":"Ballyboden","timezone":{"dstOffset":1,"gmtOffset":0,"timeZoneId":"Europe/Dublin"},"lat":53.28056,"lng":-6.31639,"population":9611},{"id":2962714,"name":"Mallow","timezone":{"dstOffset":1,"gmtOffset":0,"timeZoneId":"Europe/Dublin"},"lat":52.13333,"lng":-8.63333,"population":9495},{"id":2962019,"name":"Portmarnock","timezone":{"dstOffset":1,"gmtOffset":0,"timeZoneId":"Europe/Dublin"},"lat":53.42306,"lng":-6.1375,"population":9285},{"id":2961651,"name":"Rush","timezone":{"dstOffset":1,"gmtOffset":0,"timeZoneId":"Europe/Dublin"},"lat":53.52424,"lng":-6.10497,"population":9231},{"id":2961120,"name":"Tramore","timezone":{"dstOffset":1,"gmtOffset":0,"timeZoneId":"Europe/Dublin"},"lat":52.16235,"lng":-7.15244,"population":9164},{"id":8642910,"name":"Balally","timezone":{"dstOffset":1,"gmtOffset":0,"timeZoneId":"Europe/Dublin"},"lat":53.27504,"lng":-6.23594,"population":9051},{"id":2961872,"name":"Ratoath","timezone":{"dstOffset":1,"gmtOffset":0,"timeZoneId":"Europe/Dublin"},"lat":53.50806,"lng":-6.4625,"population":9043},{"id":2961589,"name":"Sandymount","timezone":{"dstOffset":1,"gmtOffset":0,"timeZoneId":"Europe/Dublin"},"lat":53.335,"lng":-6.21139,"population":8967},{"id":2962630,"name":"Midleton","timezone":{"dstOffset":1,"gmtOffset":0,"timeZoneId":"Europe/Dublin"},"lat":51.91526,"lng":-8.18052,"population":8891},{"id":2966131,"name":"Blackrock","timezone":{"dstOffset":1,"gmtOffset":0,"timeZoneId":"Europe/Dublin"},"lat":53.3015,"lng":-6.1778,"population":8821},{"id":3315311,"name":"Beaumont","timezone":{"dstOffset":1,"gmtOffset":0,"timeZoneId":"Europe/Dublin"},"lat":53.39139,"lng":-6.24056,"population":8609},{"id":3315378,"name":"Ballyfermot","timezone":{"dstOffset":1,"gmtOffset":0,"timeZoneId":"Europe/Dublin"},"lat":53.34528,"lng":-6.35889,"population":8558},{"id":6691010,"name":"Ballinteer","timezone":{"dstOffset":1,"gmtOffset":0,"timeZoneId":"Europe/Dublin"},"lat":53.27409,"lng":-6.25397,"population":8547},{"id":3315287,"name":"Rathgar","timezone":{"dstOffset":1,"gmtOffset":0,"timeZoneId":"Europe/Dublin"},"lat":53.31457,"lng":-6.275,"population":8394},{"id":2965599,"name":"Castleknock","timezone":{"dstOffset":1,"gmtOffset":0,"timeZoneId":"Europe/Dublin"},"lat":53.37483,"lng":-6.36336,"population":8301},{"id":2961816,"name":"Ringsend","timezone":{"dstOffset":1,"gmtOffset":0,"timeZoneId":"Europe/Dublin"},"lat":53.34194,"lng":-6.22639,"population":8202},{"id":2963436,"name":"Kildare","timezone":{"dstOffset":1,"gmtOffset":0,"timeZoneId":"Europe/Dublin"},"lat":53.15611,"lng":-6.91444,"population":8142},{"id":2966793,"name":"Baldoyle","timezone":{"dstOffset":1,"gmtOffset":0,"timeZoneId":"Europe/Dublin"},"lat":53.39972,"lng":-6.12583,"population":8043},{"id":3315204,"name":"Little Bray","timezone":{"dstOffset":1,"gmtOffset":0,"timeZoneId":"Europe/Dublin"},"lat":53.20444,"lng":-6.12083,"population":8015},{"id":6619871,"name":"Cherry Orchard","timezone":{"dstOffset":1,"gmtOffset":0,"timeZoneId":"Europe/Dublin"},"lat":53.33605,"lng":-6.37799,"population":7924},{"id":2962638,"name":"Mount Merrion","timezone":{"dstOffset":1,"gmtOffset":0,"timeZoneId":"Europe/Dublin"},"lat":53.30008,"lng":-6.21504,"population":7846},{"id":2962029,"name":"Portarlington","timezone":{"dstOffset":1,"gmtOffset":0,"timeZoneId":"Europe/Dublin"},"lat":53.16222,"lng":-7.19111,"population":7788},{"id":2962840,"name":"Longford","timezone":{"dstOffset":1,"gmtOffset":0,"timeZoneId":"Europe/Dublin"},"lat":53.72536,"lng":-7.79823,"population":7787},{"id":2961235,"name":"Terenure","timezone":{"dstOffset":1,"gmtOffset":0,"timeZoneId":"Europe/Dublin"},"lat":53.30972,"lng":-6.28528,"population":7674},{"id":6691048,"name":"Donnycarney","timezone":{"dstOffset":1,"gmtOffset":0,"timeZoneId":"Europe/Dublin"},"lat":53.3735,"lng":-6.20976,"population":7660},{"id":2961214,"name":"Thurles","timezone":{"dstOffset":1,"gmtOffset":0,"timeZoneId":"Europe/Dublin"},"lat":52.68194,"lng":-7.80222,"population":7588},{"id":2964528,"name":"Dungarvan","timezone":{"dstOffset":1,"gmtOffset":0,"timeZoneId":"Europe/Dublin"},"lat":52.08806,"lng":-7.62528,"population":7551},{"id":2963370,"name":"Killarney","timezone":{"dstOffset":1,"gmtOffset":0,"timeZoneId":"Europe/Dublin"},"lat":52.05,"lng":-9.51667,"population":7300},{"id":2961960,"name":"Raheny","timezone":{"dstOffset":1,"gmtOffset":0,"timeZoneId":"Europe/Dublin"},"lat":53.38681,"lng":-6.18067,"population":7197},{"id":7838923,"name":"Palmerstown","timezone":{"dstOffset":1,"gmtOffset":0,"timeZoneId":"Europe/Dublin"},"lat":53.35019,"lng":-6.37778,"population":7197},{"id":6691006,"name":"Booterstown","timezone":{"dstOffset":1,"gmtOffset":0,"timeZoneId":"Europe/Dublin"},"lat":53.30447,"lng":-6.19985,"population":7142},{"id":3315404,"name":"Templeogue","timezone":{"dstOffset":1,"gmtOffset":0,"timeZoneId":"Europe/Dublin"},"lat":53.29528,"lng":-6.30889,"population":7023},{"id":2962769,"name":"Lusk","timezone":{"dstOffset":1,"gmtOffset":0,"timeZoneId":"Europe/Dublin"},"lat":53.52743,"lng":-6.16423,"population":7022},{"id":2964547,"name":"Dunboyne","timezone":{"dstOffset":1,"gmtOffset":0,"timeZoneId":"Europe/Dublin"},"lat":53.4,"lng":-6.46667,"population":6959},{"id":3315282,"name":"Sallynoggin","timezone":{"dstOffset":1,"gmtOffset":0,"timeZoneId":"Europe/Dublin"},"lat":53.27917,"lng":-6.14058,"population":6916},{"id":6691017,"name":"Greenhills","timezone":{"dstOffset":1,"gmtOffset":0,"timeZoneId":"Europe/Dublin"},"lat":53.33467,"lng":-6.30302,"population":6876},{"id":2960869,"name":"Youghal","timezone":{"dstOffset":1,"gmtOffset":0,"timeZoneId":"Europe/Dublin"},"lat":51.95,"lng":-7.85056,"population":6868},{"id":3315276,"name":"Firhouse","timezone":{"dstOffset":1,"gmtOffset":0,"timeZoneId":"Europe/Dublin"},"lat":53.28167,"lng":-6.33917,"population":6859},{"id":2962222,"name":"Newtown Trim","timezone":{"dstOffset":1,"gmtOffset":0,"timeZoneId":"Europe/Dublin"},"lat":53.55611,"lng":-6.77,"population":6781},{"id":2964765,"name":"Donabate","timezone":{"dstOffset":1,"gmtOffset":0,"timeZoneId":"Europe/Dublin"},"lat":53.48722,"lng":-6.15194,"population":6778},{"id":2965484,"name":"Clane","timezone":{"dstOffset":1,"gmtOffset":0,"timeZoneId":"Europe/Dublin"},"lat":53.29139,"lng":-6.68917,"population":6702},{"id":2962252,"name":"New Ross","timezone":{"dstOffset":1,"gmtOffset":0,"timeZoneId":"Europe/Dublin"},"lat":52.39667,"lng":-6.93667,"population":6695},{"id":3306439,"name":"Nenagh Bridge","timezone":{"dstOffset":1,"gmtOffset":0,"timeZoneId":"Europe/Dublin"},"lat":52.88167,"lng":-8.19583,"population":6672},{"id":2964892,"name":"Dalkey","timezone":{"dstOffset":1,"gmtOffset":0,"timeZoneId":"Europe/Dublin"},"lat":53.27833,"lng":-6.10028,"population":6622},{"id":2966022,"name":"Bray","timezone":{"dstOffset":1,"gmtOffset":0,"timeZoneId":"Europe/Dublin"},"lat":53.20278,"lng":-6.09833,"population":6477},{"id":2965535,"name":"Cavan","timezone":{"dstOffset":1,"gmtOffset":0,"timeZoneId":"Europe/Dublin"},"lat":53.99083,"lng":-7.36056,"population":6388},{"id":2966753,"name":"Ballinasloe","timezone":{"dstOffset":1,"gmtOffset":0,"timeZoneId":"Europe/Dublin"},"lat":53.3275,"lng":-8.21944,"population":6388},{"id":2965509,"name":"Cherryville","timezone":{"dstOffset":1,"gmtOffset":0,"timeZoneId":"Europe/Dublin"},"lat":53.15694,"lng":-6.96667,"population":6380},{"id":2962283,"name":"Newcastle West","timezone":{"dstOffset":1,"gmtOffset":0,"timeZoneId":"Europe/Dublin"},"lat":52.44917,"lng":-9.06111,"population":6327},{"id":3315315,"name":"Ballymun","timezone":{"dstOffset":1,"gmtOffset":0,"timeZoneId":"Europe/Dublin"},"lat":53.39807,"lng":-6.26693,"population":6262},{"id":2960970,"name":"Westport","timezone":{"dstOffset":1,"gmtOffset":0,"timeZoneId":"Europe/Dublin"},"lat":53.8,"lng":-9.51667,"population":6200},{"id":2961099,"name":"Tuam","timezone":{"dstOffset":1,"gmtOffset":0,"timeZoneId":"Europe/Dublin"},"lat":53.51667,"lng":-8.85,"population":6130},{"id":2963962,"name":"Gorey","timezone":{"dstOffset":1,"gmtOffset":0,"timeZoneId":"Europe/Dublin"},"lat":52.67472,"lng":-6.2925,"population":6040},{"id":2962568,"name":"Monaghan","timezone":{"dstOffset":1,"gmtOffset":0,"timeZoneId":"Europe/Dublin"},"lat":54.25,"lng":-6.96667,"population":5937},{"id":3315332,"name":"Hartstown","timezone":{"dstOffset":1,"gmtOffset":0,"timeZoneId":"Europe/Dublin"},"lat":53.39306,"lng":-6.42694,"population":5882},{"id":8658946,"name":"Kinsealy-Drinan","timezone":{"dstOffset":1,"gmtOffset":0,"timeZoneId":"Europe/Dublin"},"lat":53.44395,"lng":-6.20334,"population":5814},{"id":2965726,"name":"Carrick-on-Suir","timezone":{"dstOffset":1,"gmtOffset":0,"timeZoneId":"Europe/Dublin"},"lat":52.34917,"lng":-7.41306,"population":5710},{"id":2961732,"name":"Roscommon","timezone":{"dstOffset":1,"gmtOffset":0,"timeZoneId":"Europe/Dublin"},"lat":53.63333,"lng":-8.18333,"population":5693},{"id":6691035,"name":"Darndale","timezone":{"dstOffset":1,"gmtOffset":0,"timeZoneId":"Europe/Dublin"},"lat":53.39948,"lng":-6.18886,"population":5667},{"id":2962543,"name":"Monkstown","timezone":{"dstOffset":1,"gmtOffset":0,"timeZoneId":"Europe/Dublin"},"lat":53.29308,"lng":-6.15312,"population":5555},{"id":2654332,"name":"Buncrana","timezone":{"dstOffset":1,"gmtOffset":0,"timeZoneId":"Europe/Dublin"},"lat":55.13333,"lng":-7.45,"population":5546},{"id":2963472,"name":"Kilcock","timezone":{"dstOffset":1,"gmtOffset":0,"timeZoneId":"Europe/Dublin"},"lat":53.40222,"lng":-6.67083,"population":5533},{"id":2962304,"name":"Nenagh","timezone":{"dstOffset":1,"gmtOffset":0,"timeZoneId":"Europe/Dublin"},"lat":52.86194,"lng":-8.19667,"population":5500},{"id":2966370,"name":"Bandon","timezone":{"dstOffset":1,"gmtOffset":0,"timeZoneId":"Europe/Dublin"},"lat":51.74694,"lng":-8.7425,"population":5492},{"id":2961730,"name":"Roscrea","timezone":{"dstOffset":1,"gmtOffset":0,"timeZoneId":"Europe/Dublin"},"lat":52.95111,"lng":-7.80167,"population":5403},{"id":7870938,"name":"Confey","timezone":{"dstOffset":1,"gmtOffset":0,"timeZoneId":"Europe/Dublin"},"lat":53.37923,"lng":-6.49052,"population":5389},{"id":3315200,"name":"Eadestown","timezone":{"dstOffset":1,"gmtOffset":0,"timeZoneId":"Europe/Dublin"},"lat":53.20278,"lng":-6.57806,"population":5346},{"id":3315304,"name":"Artane","timezone":{"dstOffset":1,"gmtOffset":0,"timeZoneId":"Europe/Dublin"},"lat":53.38712,"lng":-6.2138,"population":5328},{"id":2965525,"name":"Chapelizod","timezone":{"dstOffset":1,"gmtOffset":0,"timeZoneId":"Europe/Dublin"},"lat":53.34889,"lng":-6.34667,"population":5296},{"id":2961607,"name":"Sallins","timezone":{"dstOffset":1,"gmtOffset":0,"timeZoneId":"Europe/Dublin"},"lat":53.24889,"lng":-6.66611,"population":5283},{"id":7869996,"name":"Killester","timezone":{"dstOffset":1,"gmtOffset":0,"timeZoneId":"Europe/Dublin"},"lat":53.37322,"lng":-6.20431,"population":5099},{"id":2964767,"name":"Dollymount","timezone":{"dstOffset":1,"gmtOffset":0,"timeZoneId":"Europe/Dublin"},"lat":53.36489,"lng":-6.18032,"population":5070},{"id":2962800,"name":"Loughrea","timezone":{"dstOffset":1,"gmtOffset":0,"timeZoneId":"Europe/Dublin"},"lat":53.19694,"lng":-8.56694,"population":5062},{"id":2966101,"name":"Blessington","timezone":{"dstOffset":1,"gmtOffset":0,"timeZoneId":"Europe/Dublin"},"lat":53.17,"lng":-6.5325,"population":5010},{"id":2961192,"name":"Tipperary","timezone":{"dstOffset":1,"gmtOffset":0,"timeZoneId":"Europe/Dublin"},"lat":52.47333,"lng":-8.15583,"population":4976},{"id":2964320,"name":"Fermoy","timezone":{"dstOffset":1,"gmtOffset":0,"timeZoneId":"Europe/Dublin"},"lat":52.13583,"lng":-8.27583,"population":4933},{"id":2962066,"name":"Passage West","timezone":{"dstOffset":1,"gmtOffset":0,"timeZoneId":"Europe/Dublin"},"lat":51.87389,"lng":-8.34444,"population":4907},{"id":2964436,"name":"Edenderry","timezone":{"dstOffset":1,"gmtOffset":0,"timeZoneId":"Europe/Dublin"},"lat":53.34528,"lng":-7.04972,"population":4890},{"id":2966668,"name":"Ballybofey","timezone":{"dstOffset":1,"gmtOffset":0,"timeZoneId":"Europe/Dublin"},"lat":54.8,"lng":-7.78333,"population":4852},{"id":2963528,"name":"Kells","timezone":{"dstOffset":1,"gmtOffset":0,"timeZoneId":"Europe/Dublin"},"lat":53.72639,"lng":-6.87917,"population":4820},{"id":2962153,"name":"Oranmore","timezone":{"dstOffset":1,"gmtOffset":0,"timeZoneId":"Europe/Dublin"},"lat":53.26833,"lng":-8.92,"population":4799},{"id":2963722,"name":"Howth","timezone":{"dstOffset":1,"gmtOffset":0,"timeZoneId":"Europe/Dublin"},"lat":53.38778,"lng":-6.06528,"population":4574},{"id":6691032,"name":"Bonnybrook","timezone":{"dstOffset":1,"gmtOffset":0,"timeZoneId":"Europe/Dublin"},"lat":53.39835,"lng":-6.20749,"population":4554},{"id":2965694,"name":"Carrigtohill","timezone":{"dstOffset":1,"gmtOffset":0,"timeZoneId":"Europe/Dublin"},"lat":51.90833,"lng":-8.26333,"population":4551},{"id":2966154,"name":"Birr","timezone":{"dstOffset":1,"gmtOffset":0,"timeZoneId":"Europe/Dublin"},"lat":53.09139,"lng":-7.91333,"population":4549},{"id":6693222,"name":"Bayside","timezone":{"dstOffset":1,"gmtOffset":0,"timeZoneId":"Europe/Dublin"},"lat":53.38895,"lng":-6.14041,"population":4511},{"id":6691003,"name":"Clonskeagh","timezone":{"dstOffset":1,"gmtOffset":0,"timeZoneId":"Europe/Dublin"},"lat":53.31467,"lng":-6.23148,"population":4500},{"id":3315312,"name":"Drumcondra","timezone":{"dstOffset":1,"gmtOffset":0,"timeZoneId":"Europe/Dublin"},"lat":53.37058,"lng":-6.25298,"population":4465},{"id":7648535,"name":"Moyross","timezone":{"dstOffset":1,"gmtOffset":0,"timeZoneId":"Europe/Dublin"},"lat":52.68198,"lng":-8.63955,"population":4448},{"id":3315319,"name":"Cabra","timezone":{"dstOffset":1,"gmtOffset":0,"timeZoneId":"Europe/Dublin"},"lat":53.36694,"lng":-6.29444,"population":4389},{"id":2963827,"name":"Gweedore","timezone":{"dstOffset":1,"gmtOffset":0,"timeZoneId":"Europe/Dublin"},"lat":55.05028,"lng":-8.23194,"population":4200},{"id":2962864,"name":"Listowel","timezone":{"dstOffset":1,"gmtOffset":0,"timeZoneId":"Europe/Dublin"},"lat":52.44639,"lng":-9.485,"population":4143},{"id":2965402,"name":"Clonakilty","timezone":{"dstOffset":1,"gmtOffset":0,"timeZoneId":"Europe/Dublin"},"lat":51.62306,"lng":-8.87056,"population":4065},{"id":2963460,"name":"Kilcoole","timezone":{"dstOffset":1,"gmtOffset":0,"timeZoneId":"Europe/Dublin"},"lat":53.10278,"lng":-6.065,"population":4049},{"id":6691002,"name":"Milltown","timezone":{"dstOffset":1,"gmtOffset":0,"timeZoneId":"Europe/Dublin"},"lat":53.31301,"lng":-6.2453,"population":4049},{"id":2966925,"name":"Ardee","timezone":{"dstOffset":1,"gmtOffset":0,"timeZoneId":"Europe/Dublin"},"lat":53.85972,"lng":-6.54056,"population":4008},{"id":2965733,"name":"Carrickmacross","timezone":{"dstOffset":1,"gmtOffset":0,"timeZoneId":"Europe/Dublin"},"lat":53.97278,"lng":-6.71889,"population":3995},{"id":2964558,"name":"Duleek","timezone":{"dstOffset":1,"gmtOffset":0,"timeZoneId":"Europe/Dublin"},"lat":53.65667,"lng":-6.41917,"population":3988},{"id":2965727,"name":"Carrick on Shannon","timezone":{"dstOffset":1,"gmtOffset":0,"timeZoneId":"Europe/Dublin"},"lat":53.94694,"lng":-8.09,"population":3980},{"id":2961079,"name":"Tullow","timezone":{"dstOffset":1,"gmtOffset":0,"timeZoneId":"Europe/Dublin"},"lat":52.80028,"lng":-6.73694,"population":3972},{"id":2966843,"name":"Athenry","timezone":{"dstOffset":1,"gmtOffset":0,"timeZoneId":"Europe/Dublin"},"lat":53.29639,"lng":-8.74306,"population":3950},{"id":2964472,"name":"Dunshaughlin","timezone":{"dstOffset":1,"gmtOffset":0,"timeZoneId":"Europe/Dublin"},"lat":53.5125,"lng":-6.54,"population":3903},{"id":2963155,"name":"Kinsale","timezone":{"dstOffset":1,"gmtOffset":0,"timeZoneId":"Europe/Dublin"},"lat":51.7075,"lng":-8.53056,"population":3843},{"id":2961305,"name":"Sutton","timezone":{"dstOffset":1,"gmtOffset":0,"timeZoneId":"Europe/Dublin"},"lat":53.38947,"lng":-6.11059,"population":3837},{"id":7838916,"name":"Fairview","timezone":{"dstOffset":1,"gmtOffset":0,"timeZoneId":"Europe/Dublin"},"lat":53.36597,"lng":-6.23985,"population":3821},{"id":2962556,"name":"Monasterevin","timezone":{"dstOffset":1,"gmtOffset":0,"timeZoneId":"Europe/Dublin"},"lat":53.14056,"lng":-7.06639,"population":3710},{"id":2962587,"name":"Mitchelstown","timezone":{"dstOffset":1,"gmtOffset":0,"timeZoneId":"Europe/Dublin"},"lat":52.26583,"lng":-8.26806,"population":3677},{"id":2965516,"name":"Ráth Luirc","timezone":{"dstOffset":1,"gmtOffset":0,"timeZoneId":"Europe/Dublin"},"lat":52.35,"lng":-8.68333,"population":3672},{"id":2962804,"name":"Loughlinstown","timezone":{"dstOffset":1,"gmtOffset":0,"timeZoneId":"Europe/Dublin"},"lat":53.24389,"lng":-6.13306,"population":3665},{"id":6690994,"name":"Rialto","timezone":{"dstOffset":1,"gmtOffset":0,"timeZoneId":"Europe/Dublin"},"lat":53.33625,"lng":-6.29718,"population":3652},{"id":2964102,"name":"Glasnevin","timezone":{"dstOffset":1,"gmtOffset":0,"timeZoneId":"Europe/Dublin"},"lat":53.38028,"lng":-6.26417,"population":3633},{"id":2965873,"name":"Caher","timezone":{"dstOffset":1,"gmtOffset":0,"timeZoneId":"Europe/Dublin"},"lat":52.37694,"lng":-7.92167,"population":3578},{"id":2962476,"name":"Mountmellick","timezone":{"dstOffset":1,"gmtOffset":0,"timeZoneId":"Europe/Dublin"},"lat":53.11361,"lng":-7.32,"population":3547},{"id":2963444,"name":"Kilcullen","timezone":{"dstOffset":1,"gmtOffset":0,"timeZoneId":"Europe/Dublin"},"lat":53.13028,"lng":-6.74444,"population":3473},{"id":2961929,"name":"Rathcoole","timezone":{"dstOffset":1,"gmtOffset":0,"timeZoneId":"Europe/Dublin"},"lat":53.28278,"lng":-6.47278,"population":3421},{"id":2965471,"name":"Claremorris","timezone":{"dstOffset":1,"gmtOffset":0,"timeZoneId":"Europe/Dublin"},"lat":53.71667,"lng":-9,"population":3412},{"id":2964503,"name":"Dún Lúiche","timezone":{"dstOffset":1,"gmtOffset":0,"timeZoneId":"Europe/Dublin"},"lat":55.01667,"lng":-8.1,"population":3400},{"id":2966356,"name":"Bantry","timezone":{"dstOffset":1,"gmtOffset":0,"timeZoneId":"Europe/Dublin"},"lat":51.68333,"lng":-9.45,"population":3348},{"id":2961129,"name":"Tower","timezone":{"dstOffset":1,"gmtOffset":0,"timeZoneId":"Europe/Dublin"},"lat":51.91667,"lng":-8.6,"population":3306},{"id":2965482,"name":"Clara","timezone":{"dstOffset":1,"gmtOffset":0,"timeZoneId":"Europe/Dublin"},"lat":53.3425,"lng":-7.61389,"population":3242},{"id":2962745,"name":"Macroom","timezone":{"dstOffset":1,"gmtOffset":0,"timeZoneId":"Europe/Dublin"},"lat":51.9,"lng":-8.95,"population":3169},{"id":2961366,"name":"Stamullin","timezone":{"dstOffset":1,"gmtOffset":0,"timeZoneId":"Europe/Dublin"},"lat":53.62889,"lng":-6.26833,"population":3130},{"id":3314724,"name":"Kill","timezone":{"dstOffset":1,"gmtOffset":0,"timeZoneId":"Europe/Dublin"},"lat":53.25139,"lng":-6.59167,"population":3095},{"id":2966800,"name":"Bagenalstown","timezone":{"dstOffset":1,"gmtOffset":0,"timeZoneId":"Europe/Dublin"},"lat":52.70031,"lng":-6.96181,"population":3033},{"id":2965649,"name":"Castleblayney","timezone":{"dstOffset":1,"gmtOffset":0,"timeZoneId":"Europe/Dublin"},"lat":54.11667,"lng":-6.73333,"population":3006},{"id":2966130,"name":"Blackrock","timezone":{"dstOffset":1,"gmtOffset":0,"timeZoneId":"Europe/Dublin"},"lat":53.96405,"lng":-6.36514,"population":3000},{"id":2961884,"name":"Rathnew","timezone":{"dstOffset":1,"gmtOffset":0,"timeZoneId":"Europe/Dublin"},"lat":52.99056,"lng":-6.08528,"population":2964},{"id":2964407,"name":"Enfield","timezone":{"dstOffset":1,"gmtOffset":0,"timeZoneId":"Europe/Dublin"},"lat":53.41419,"lng":-6.83229,"population":2929},{"id":2965092,"name":"Courtown","timezone":{"dstOffset":1,"gmtOffset":0,"timeZoneId":"Europe/Dublin"},"lat":52.64424,"lng":-6.22899,"population":2857},{"id":3305634,"name":"Annacotty","timezone":{"dstOffset":1,"gmtOffset":0,"timeZoneId":"Europe/Dublin"},"lat":52.66806,"lng":-8.54722,"population":2856},{"id":2965664,"name":"Cashel","timezone":{"dstOffset":1,"gmtOffset":0,"timeZoneId":"Europe/Dublin"},"lat":52.51583,"lng":-7.88556,"population":2798},{"id":3314017,"name":"Moate","timezone":{"dstOffset":1,"gmtOffset":0,"timeZoneId":"Europe/Dublin"},"lat":53.39389,"lng":-7.71722,"population":2731},{"id":2963218,"name":"Kilrush","timezone":{"dstOffset":1,"gmtOffset":0,"timeZoneId":"Europe/Dublin"},"lat":52.63972,"lng":-9.48333,"population":2712},{"id":2966715,"name":"Ballinrobe","timezone":{"dstOffset":1,"gmtOffset":0,"timeZoneId":"Europe/Dublin"},"lat":53.63333,"lng":-9.23333,"population":2704},{"id":2966406,"name":"Ballyshannon","timezone":{"dstOffset":1,"gmtOffset":0,"timeZoneId":"Europe/Dublin"},"lat":54.5,"lng":-8.18333,"population":2683},{"id":2963158,"name":"Kinnegad","timezone":{"dstOffset":1,"gmtOffset":0,"timeZoneId":"Europe/Dublin"},"lat":53.45222,"lng":-7.09972,"population":2662},{"id":2962281,"name":"Newcastle","timezone":{"dstOffset":1,"gmtOffset":0,"timeZoneId":"Europe/Dublin"},"lat":53.30111,"lng":-6.50222,"population":2659},{"id":2963958,"name":"Gort","timezone":{"dstOffset":1,"gmtOffset":0,"timeZoneId":"Europe/Dublin"},"lat":53.06639,"lng":-8.81667,"population":2644},{"id":6691030,"name":"Coolock","timezone":{"dstOffset":1,"gmtOffset":0,"timeZoneId":"Europe/Dublin"},"lat":53.3887,"lng":-6.19998,"population":2632},{"id":2964752,"name":"Donegal","timezone":{"dstOffset":1,"gmtOffset":0,"timeZoneId":"Europe/Dublin"},"lat":54.65,"lng":-8.11667,"population":2607},{"id":2966550,"name":"Ballyjamesduff","timezone":{"dstOffset":1,"gmtOffset":0,"timeZoneId":"Europe/Dublin"},"lat":53.86528,"lng":-7.20278,"population":2568},{"id":2965761,"name":"Carndonagh","timezone":{"dstOffset":1,"gmtOffset":0,"timeZoneId":"Europe/Dublin"},"lat":55.25,"lng":-7.26667,"population":2534},{"id":2966796,"name":"Bailieborough","timezone":{"dstOffset":1,"gmtOffset":0,"timeZoneId":"Europe/Dublin"},"lat":53.91667,"lng":-6.96667,"population":2530},{"id":2965604,"name":"Castleisland","timezone":{"dstOffset":1,"gmtOffset":0,"timeZoneId":"Europe/Dublin"},"lat":52.23333,"lng":-9.46667,"population":2513},{"id":2961470,"name":"Sixmilebridge","timezone":{"dstOffset":1,"gmtOffset":0,"timeZoneId":"Europe/Dublin"},"lat":52.74139,"lng":-8.77417,"population":2507},{"id":2966779,"name":"Ballina","timezone":{"dstOffset":1,"gmtOffset":0,"timeZoneId":"Europe/Dublin"},"lat":52.80778,"lng":-8.43556,"population":2442},{"id":2966107,"name":"Blarney","timezone":{"dstOffset":1,"gmtOffset":0,"timeZoneId":"Europe/Dublin"},"lat":51.93333,"lng":-8.56667,"population":2437},{"id":7870989,"name":"Newtownmountkennedy","timezone":{"dstOffset":1,"gmtOffset":0,"timeZoneId":"Europe/Dublin"},"lat":53.09052,"lng":-6.11149,"population":2410},{"id":2966848,"name":"Athboy","timezone":{"dstOffset":1,"gmtOffset":0,"timeZoneId":"Europe/Dublin"},"lat":53.62327,"lng":-6.91434,"population":2397},{"id":2961938,"name":"Rathangan","timezone":{"dstOffset":1,"gmtOffset":0,"timeZoneId":"Europe/Dublin"},"lat":53.22139,"lng":-6.995,"population":2374},{"id":2965841,"name":"Callan","timezone":{"dstOffset":1,"gmtOffset":0,"timeZoneId":"Europe/Dublin"},"lat":52.545,"lng":-7.39111,"population":2330},{"id":2963169,"name":"Kingscourt","timezone":{"dstOffset":1,"gmtOffset":0,"timeZoneId":"Europe/Dublin"},"lat":53.90806,"lng":-6.80556,"population":2326},{"id":2966566,"name":"Ballyhaunis","timezone":{"dstOffset":1,"gmtOffset":0,"timeZoneId":"Europe/Dublin"},"lat":53.76667,"lng":-8.76667,"population":2312},{"id":2961006,"name":"Virginia","timezone":{"dstOffset":1,"gmtOffset":0,"timeZoneId":"Europe/Dublin"},"lat":53.83389,"lng":-7.07556,"population":2282},{"id":2961224,"name":"Thomastown","timezone":{"dstOffset":1,"gmtOffset":0,"timeZoneId":"Europe/Dublin"},"lat":52.52667,"lng":-7.13722,"population":2273},{"id":2961237,"name":"Templemore","timezone":{"dstOffset":1,"gmtOffset":0,"timeZoneId":"Europe/Dublin"},"lat":52.79472,"lng":-7.83389,"population":2264},{"id":2963555,"name":"Kanturk","timezone":{"dstOffset":1,"gmtOffset":0,"timeZoneId":"Europe/Dublin"},"lat":52.16667,"lng":-8.9,"population":2263},{"id":2961994,"name":"Prosperous","timezone":{"dstOffset":1,"gmtOffset":0,"timeZoneId":"Europe/Dublin"},"lat":53.29028,"lng":-6.75389,"population":2248},{"id":2966044,"name":"Boyle","timezone":{"dstOffset":1,"gmtOffset":0,"timeZoneId":"Europe/Dublin"},"lat":53.96667,"lng":-8.3,"population":2199},{"id":2963522,"name":"Kenmare","timezone":{"dstOffset":1,"gmtOffset":0,"timeZoneId":"Europe/Dublin"},"lat":51.88333,"lng":-9.58333,"population":2175},{"id":2961636,"name":"Saggart","timezone":{"dstOffset":1,"gmtOffset":0,"timeZoneId":"Europe/Dublin"},"lat":53.28028,"lng":-6.44444,"population":2144},{"id":2962170,"name":"Old Kilcullen","timezone":{"dstOffset":1,"gmtOffset":0,"timeZoneId":"Europe/Dublin"},"lat":53.10639,"lng":-6.76528,"population":2110},{"id":2961459,"name":"Skibbereen","timezone":{"dstOffset":1,"gmtOffset":0,"timeZoneId":"Europe/Dublin"},"lat":51.55,"lng":-9.26667,"population":2098},{"id":2964985,"name":"Crosshaven","timezone":{"dstOffset":1,"gmtOffset":0,"timeZoneId":"Europe/Dublin"},"lat":51.79833,"lng":-8.30083,"population":2093},{"id":2963311,"name":"Killorglin","timezone":{"dstOffset":1,"gmtOffset":0,"timeZoneId":"Europe/Dublin"},"lat":52.1,"lng":-9.78333,"population":2082},{"id":2966375,"name":"Baltinglass","timezone":{"dstOffset":1,"gmtOffset":0,"timeZoneId":"Europe/Dublin"},"lat":52.93722,"lng":-6.70917,"population":2061},{"id":2965449,"name":"Clifden","timezone":{"dstOffset":1,"gmtOffset":0,"timeZoneId":"Europe/Dublin"},"lat":53.48907,"lng":-10.0191,"population":2056},{"id":2965932,"name":"Newtownbarry","timezone":{"dstOffset":1,"gmtOffset":0,"timeZoneId":"Europe/Dublin"},"lat":52.6553,"lng":-6.65359,"population":2012},{"id":2967095,"name":"Abbeyfeale","timezone":{"dstOffset":1,"gmtOffset":0,"timeZoneId":"Europe/Dublin"},"lat":52.38139,"lng":-9.3025,"population":2007},{"id":2965420,"name":"Clogherhead","timezone":{"dstOffset":1,"gmtOffset":0,"timeZoneId":"Europe/Dublin"},"lat":53.79361,"lng":-6.2375,"population":1993},{"id":2965570,"name":"Castlerea","timezone":{"dstOffset":1,"gmtOffset":0,"timeZoneId":"Europe/Dublin"},"lat":53.76667,"lng":-8.5,"population":1985},{"id":2964782,"name":"Dingle","timezone":{"dstOffset":1,"gmtOffset":0,"timeZoneId":"Europe/Dublin"},"lat":52.14083,"lng":-10.26889,"population":1965},{"id":3305640,"name":"Castleconnell","timezone":{"dstOffset":1,"gmtOffset":0,"timeZoneId":"Europe/Dublin"},"lat":52.71389,"lng":-8.49944,"population":1917},{"id":2966342,"name":"Barna","timezone":{"dstOffset":1,"gmtOffset":0,"timeZoneId":"Europe/Dublin"},"lat":53.25194,"lng":-9.14972,"population":1878},{"id":2966378,"name":"Balrothery","timezone":{"dstOffset":1,"gmtOffset":0,"timeZoneId":"Europe/Dublin"},"lat":53.58828,"lng":-6.18728,"population":1866},{"id":2965929,"name":"Bundoran","timezone":{"dstOffset":1,"gmtOffset":0,"timeZoneId":"Europe/Dublin"},"lat":54.47782,"lng":-8.28094,"population":1865},{"id":2965367,"name":"Clones","timezone":{"dstOffset":1,"gmtOffset":0,"timeZoneId":"Europe/Dublin"},"lat":54.18333,"lng":-7.23333,"population":1834},{"id":2967092,"name":"Abbeyleix","timezone":{"dstOffset":1,"gmtOffset":0,"timeZoneId":"Europe/Dublin"},"lat":52.89917,"lng":-7.3575,"population":1827},{"id":2966784,"name":"Ballaghaderreen","timezone":{"dstOffset":1,"gmtOffset":0,"timeZoneId":"Europe/Dublin"},"lat":53.9,"lng":-8.58333,"population":1822},{"id":2964401,"name":"Enniskerry","timezone":{"dstOffset":1,"gmtOffset":0,"timeZoneId":"Europe/Dublin"},"lat":53.1925,"lng":-6.16917,"population":1811},{"id":2962257,"name":"Newport","timezone":{"dstOffset":1,"gmtOffset":0,"timeZoneId":"Europe/Dublin"},"lat":52.71111,"lng":-8.40972,"population":1806},{"id":2961107,"name":"Trim","timezone":{"dstOffset":1,"gmtOffset":0,"timeZoneId":"Europe/Dublin"},"lat":53.555,"lng":-6.79167,"population":1800},{"id":6857857,"name":"Charlesland","timezone":{"dstOffset":1,"gmtOffset":0,"timeZoneId":"Europe/Dublin"},"lat":53.12771,"lng":-6.06347,"population":1800},{"id":2964504,"name":"Dunleer","timezone":{"dstOffset":1,"gmtOffset":0,"timeZoneId":"Europe/Dublin"},"lat":53.835,"lng":-6.39611,"population":1786},{"id":2962262,"name":"Newmarket on Fergus","timezone":{"dstOffset":1,"gmtOffset":0,"timeZoneId":"Europe/Dublin"},"lat":52.76,"lng":-8.89556,"population":1773},{"id":3315130,"name":"Valleymount","timezone":{"dstOffset":1,"gmtOffset":0,"timeZoneId":"Europe/Dublin"},"lat":53.10389,"lng":-6.55361,"population":1756},{"id":2961182,"name":"Tobercurry","timezone":{"dstOffset":1,"gmtOffset":0,"timeZoneId":"Europe/Dublin"},"lat":54.05,"lng":-8.73333,"population":1747},{"id":2964434,"name":"Edgeworthstown","timezone":{"dstOffset":1,"gmtOffset":0,"timeZoneId":"Europe/Dublin"},"lat":53.7,"lng":-7.61667,"population":1744},{"id":2966690,"name":"Ballivor","timezone":{"dstOffset":1,"gmtOffset":0,"timeZoneId":"Europe/Dublin"},"lat":53.53167,"lng":-6.96111,"population":1727},{"id":2965645,"name":"Castlebridge","timezone":{"dstOffset":1,"gmtOffset":0,"timeZoneId":"Europe/Dublin"},"lat":52.38639,"lng":-6.44944,"population":1726},{"id":2965158,"name":"Cootehill","timezone":{"dstOffset":1,"gmtOffset":0,"timeZoneId":"Europe/Dublin"},"lat":54.0725,"lng":-7.08194,"population":1713},{"id":2962025,"name":"Portlaw","timezone":{"dstOffset":1,"gmtOffset":0,"timeZoneId":"Europe/Dublin"},"lat":52.28833,"lng":-7.32056,"population":1696},{"id":2962465,"name":"Mountrath","timezone":{"dstOffset":1,"gmtOffset":0,"timeZoneId":"Europe/Dublin"},"lat":52.99889,"lng":-7.47278,"population":1661},{"id":2962945,"name":"Lifford","timezone":{"dstOffset":1,"gmtOffset":0,"timeZoneId":"Europe/Dublin"},"lat":54.83194,"lng":-7.48361,"population":1658},{"id":2966371,"name":"Banagher","timezone":{"dstOffset":1,"gmtOffset":0,"timeZoneId":"Europe/Dublin"},"lat":53.18861,"lng":-7.98667,"population":1653},{"id":2963275,"name":"Kilmallock","timezone":{"dstOffset":1,"gmtOffset":0,"timeZoneId":"Europe/Dublin"},"lat":52.4,"lng":-8.57722,"population":1635},{"id":2963025,"name":"Strandhill","timezone":{"dstOffset":1,"gmtOffset":0,"timeZoneId":"Europe/Dublin"},"lat":54.27194,"lng":-8.59333,"population":1596},{"id":2961918,"name":"Rathdrum","timezone":{"dstOffset":1,"gmtOffset":0,"timeZoneId":"Europe/Dublin"},"lat":52.92639,"lng":-6.23556,"population":1586},{"id":2964496,"name":"Dunmanway","timezone":{"dstOffset":1,"gmtOffset":0,"timeZoneId":"Europe/Dublin"},"lat":51.71667,"lng":-9.11667,"population":1585},{"id":2962613,"name":"Millstreet","timezone":{"dstOffset":1,"gmtOffset":0,"timeZoneId":"Europe/Dublin"},"lat":52.06667,"lng":-9.06667,"population":1574},{"id":2966515,"name":"Ballymahon","timezone":{"dstOffset":1,"gmtOffset":0,"timeZoneId":"Europe/Dublin"},"lat":53.56667,"lng":-7.76667,"population":1563},{"id":2965276,"name":"Cloyne","timezone":{"dstOffset":1,"gmtOffset":0,"timeZoneId":"Europe/Dublin"},"lat":51.86278,"lng":-8.12444,"population":1562},{"id":2962440,"name":"Moycullen","timezone":{"dstOffset":1,"gmtOffset":0,"timeZoneId":"Europe/Dublin"},"lat":53.33783,"lng":-9.18002,"population":1559},{"id":2964492,"name":"Dunmore East","timezone":{"dstOffset":1,"gmtOffset":0,"timeZoneId":"Europe/Dublin"},"lat":52.15139,"lng":-6.98611,"population":1559},{"id":2964817,"name":"Derrybeg","timezone":{"dstOffset":1,"gmtOffset":0,"timeZoneId":"Europe/Dublin"},"lat":55.08333,"lng":-8.28944,"population":1553},{"id":2961905,"name":"Rathkeale","timezone":{"dstOffset":1,"gmtOffset":0,"timeZoneId":"Europe/Dublin"},"lat":52.52444,"lng":-8.93806,"population":1550},{"id":2961690,"name":"Rosslare","timezone":{"dstOffset":1,"gmtOffset":0,"timeZoneId":"Europe/Dublin"},"lat":52.27583,"lng":-6.38444,"population":1547},{"id":2963905,"name":"Graiguenamanagh","timezone":{"dstOffset":1,"gmtOffset":0,"timeZoneId":"Europe/Dublin"},"lat":52.54028,"lng":-6.95472,"population":1543},{"id":2964310,"name":"Fethard","timezone":{"dstOffset":1,"gmtOffset":0,"timeZoneId":"Europe/Dublin"},"lat":52.46722,"lng":-7.69111,"population":1541},{"id":2964822,"name":"Derrinturn","timezone":{"dstOffset":1,"gmtOffset":0,"timeZoneId":"Europe/Dublin"},"lat":53.34167,"lng":-6.94111,"population":1541},{"id":2966492,"name":"Ballymote","timezone":{"dstOffset":1,"gmtOffset":0,"timeZoneId":"Europe/Dublin"},"lat":54.08333,"lng":-8.51667,"population":1539},{"id":2961924,"name":"Rathcormack","timezone":{"dstOffset":1,"gmtOffset":0,"timeZoneId":"Europe/Dublin"},"lat":52.07694,"lng":-8.28194,"population":1534},{"id":2962010,"name":"Portumna","timezone":{"dstOffset":1,"gmtOffset":0,"timeZoneId":"Europe/Dublin"},"lat":53.08917,"lng":-8.21889,"population":1530},{"id":2962580,"name":"Moate","timezone":{"dstOffset":1,"gmtOffset":0,"timeZoneId":"Europe/Dublin"},"lat":53.55,"lng":-7.71667,"population":1504},{"id":2961770,"name":"Rochfortbridge","timezone":{"dstOffset":1,"gmtOffset":0,"timeZoneId":"Europe/Dublin"},"lat":53.41417,"lng":-7.29611,"population":1494},{"id":2962450,"name":"Moville","timezone":{"dstOffset":1,"gmtOffset":0,"timeZoneId":"Europe/Dublin"},"lat":55.18333,"lng":-7.05,"population":1481},{"id":2965643,"name":"Castlecomer","timezone":{"dstOffset":1,"gmtOffset":0,"timeZoneId":"Europe/Dublin"},"lat":52.80611,"lng":-7.21056,"population":1456},{"id":3315010,"name":"Ashford","timezone":{"dstOffset":1,"gmtOffset":0,"timeZoneId":"Europe/Dublin"},"lat":53.00833,"lng":-6.11139,"population":1449},{"id":2961231,"name":"Termonfeckin","timezone":{"dstOffset":1,"gmtOffset":0,"timeZoneId":"Europe/Dublin"},"lat":53.76333,"lng":-6.26778,"population":1443},{"id":2965226,"name":"Convoy","timezone":{"dstOffset":1,"gmtOffset":0,"timeZoneId":"Europe/Dublin"},"lat":54.86083,"lng":-7.66556,"population":1438},{"id":2961299,"name":"Swinford","timezone":{"dstOffset":1,"gmtOffset":0,"timeZoneId":"Europe/Dublin"},"lat":53.95,"lng":-8.95,"population":1435},{"id":2966906,"name":"Ardnacrusha","timezone":{"dstOffset":1,"gmtOffset":0,"timeZoneId":"Europe/Dublin"},"lat":52.70908,"lng":-8.61431,"population":1414},{"id":2965632,"name":"Castledermot","timezone":{"dstOffset":1,"gmtOffset":0,"timeZoneId":"Europe/Dublin"},"lat":52.90889,"lng":-6.84222,"population":1398},{"id":2962179,"name":"Olcastle","timezone":{"dstOffset":1,"gmtOffset":0,"timeZoneId":"Europe/Dublin"},"lat":53.76648,"lng":-7.16284,"population":1384},{"id":2962827,"name":"Longwood","timezone":{"dstOffset":1,"gmtOffset":0,"timeZoneId":"Europe/Dublin"},"lat":53.45389,"lng":-6.92194,"population":1378},{"id":2963036,"name":"Lanesborough","timezone":{"dstOffset":1,"gmtOffset":0,"timeZoneId":"Europe/Dublin"},"lat":53.66667,"lng":-7.98333,"population":1377},{"id":3230840,"name":"Portraine","timezone":{"dstOffset":1,"gmtOffset":0,"timeZoneId":"Europe/Dublin"},"lat":53.49667,"lng":-6.11111,"population":1372},{"id":2965248,"name":"Collooney","timezone":{"dstOffset":1,"gmtOffset":0,"timeZoneId":"Europe/Dublin"},"lat":54.18333,"lng":-8.5,"population":1369},{"id":2966817,"name":"Aughrim","timezone":{"dstOffset":1,"gmtOffset":0,"timeZoneId":"Europe/Dublin"},"lat":52.85333,"lng":-6.3275,"population":1364},{"id":2964318,"name":"Ferns","timezone":{"dstOffset":1,"gmtOffset":0,"timeZoneId":"Europe/Dublin"},"lat":52.58833,"lng":-6.49972,"population":1362},{"id":2961077,"name":"Tullyallen","timezone":{"dstOffset":1,"gmtOffset":0,"timeZoneId":"Europe/Dublin"},"lat":53.73611,"lng":-6.42278,"population":1358},{"id":2966658,"name":"Ballybunnion","timezone":{"dstOffset":1,"gmtOffset":0,"timeZoneId":"Europe/Dublin"},"lat":52.51108,"lng":-9.67097,"population":1354},{"id":2961450,"name":"Slane","timezone":{"dstOffset":1,"gmtOffset":0,"timeZoneId":"Europe/Dublin"},"lat":53.71,"lng":-6.54333,"population":1349},{"id":7838897,"name":"Ballisodare","timezone":{"dstOffset":1,"gmtOffset":0,"timeZoneId":"Europe/Dublin"},"lat":54.2111,"lng":-8.50865,"population":1344},{"id":2962706,"name":"Manorhamilton","timezone":{"dstOffset":1,"gmtOffset":0,"timeZoneId":"Europe/Dublin"},"lat":54.30639,"lng":-8.17611,"population":1336},{"id":2962144,"name":"Oughterard","timezone":{"dstOffset":1,"gmtOffset":0,"timeZoneId":"Europe/Dublin"},"lat":53.41667,"lng":-9.33333,"population":1333},{"id":2964233,"name":"Foxford","timezone":{"dstOffset":1,"gmtOffset":0,"timeZoneId":"Europe/Dublin"},"lat":53.9807,"lng":-9.11551,"population":1326},{"id":2963295,"name":"Killybegs","timezone":{"dstOffset":1,"gmtOffset":0,"timeZoneId":"Europe/Dublin"},"lat":54.63333,"lng":-8.45,"population":1297},{"id":2963376,"name":"Killaloe","timezone":{"dstOffset":1,"gmtOffset":0,"timeZoneId":"Europe/Dublin"},"lat":52.80667,"lng":-8.44361,"population":1292},{"id":3315082,"name":"Kilpedder","timezone":{"dstOffset":1,"gmtOffset":0,"timeZoneId":"Europe/Dublin"},"lat":53.10917,"lng":-6.10667,"population":1287},{"id":2965865,"name":"Caherconlish","timezone":{"dstOffset":1,"gmtOffset":0,"timeZoneId":"Europe/Dublin"},"lat":52.59361,"lng":-8.47028,"population":1279},{"id":2965590,"name":"Castlemartyr","timezone":{"dstOffset":1,"gmtOffset":0,"timeZoneId":"Europe/Dublin"},"lat":51.91028,"lng":-8.05389,"population":1277},{"id":2966201,"name":"Belturbet","timezone":{"dstOffset":1,"gmtOffset":0,"timeZoneId":"Europe/Dublin"},"lat":54.1,"lng":-7.45,"population":1277},{"id":2962389,"name":"Muff","timezone":{"dstOffset":1,"gmtOffset":0,"timeZoneId":"Europe/Dublin"},"lat":55.06667,"lng":-7.26667,"population":1271},{"id":2962522,"name":"Moroe","timezone":{"dstOffset":1,"gmtOffset":0,"timeZoneId":"Europe/Dublin"},"lat":52.65111,"lng":-8.39611,"population":1271},{"id":2961873,"name":"Rathwire","timezone":{"dstOffset":1,"gmtOffset":0,"timeZoneId":"Europe/Dublin"},"lat":53.50766,"lng":-7.1351,"population":1226},{"id":2963658,"name":"Inishcrone","timezone":{"dstOffset":1,"gmtOffset":0,"timeZoneId":"Europe/Dublin"},"lat":54.21667,"lng":-9.1,"population":1223},{"id":2965474,"name":"Claregalway","timezone":{"dstOffset":1,"gmtOffset":0,"timeZoneId":"Europe/Dublin"},"lat":53.33861,"lng":-8.945,"population":1217},{"id":2961897,"name":"Rathmelton","timezone":{"dstOffset":1,"gmtOffset":0,"timeZoneId":"Europe/Dublin"},"lat":55.03673,"lng":-7.64923,"population":1212},{"id":2961920,"name":"Rathdowney","timezone":{"dstOffset":1,"gmtOffset":0,"timeZoneId":"Europe/Dublin"},"lat":52.85472,"lng":-7.58028,"population":1208},{"id":2963499,"name":"Kilbeggan","timezone":{"dstOffset":1,"gmtOffset":0,"timeZoneId":"Europe/Dublin"},"lat":53.36944,"lng":-7.50333,"population":1199},{"id":3226389,"name":"Castletown","timezone":{"dstOffset":1,"gmtOffset":0,"timeZoneId":"Europe/Dublin"},"lat":52.72306,"lng":-6.18944,"population":1195},{"id":2962539,"name":"Moone","timezone":{"dstOffset":1,"gmtOffset":0,"timeZoneId":"Europe/Dublin"},"lat":52.97556,"lng":-6.815,"population":1195},{"id":2962045,"name":"Piltown","timezone":{"dstOffset":1,"gmtOffset":0,"timeZoneId":"Europe/Dublin"},"lat":52.35333,"lng":-7.34028,"population":1187},{"id":2964524,"name":"Dunglow","timezone":{"dstOffset":1,"gmtOffset":0,"timeZoneId":"Europe/Dublin"},"lat":54.95111,"lng":-8.35917,"population":1183},{"id":2965852,"name":"Cahersiveen","timezone":{"dstOffset":1,"gmtOffset":0,"timeZoneId":"Europe/Dublin"},"lat":51.94861,"lng":-10.22222,"population":1168},{"id":2962540,"name":"Mooncoin","timezone":{"dstOffset":1,"gmtOffset":0,"timeZoneId":"Europe/Dublin"},"lat":52.28944,"lng":-7.24833,"population":1166},{"id":2964322,"name":"Ferbane","timezone":{"dstOffset":1,"gmtOffset":0,"timeZoneId":"Europe/Dublin"},"lat":53.26944,"lng":-7.82694,"population":1165},{"id":2960987,"name":"Watergrasshill","timezone":{"dstOffset":1,"gmtOffset":0,"timeZoneId":"Europe/Dublin"},"lat":52.01139,"lng":-8.34417,"population":1161},{"id":2961944,"name":"Raphoe","timezone":{"dstOffset":1,"gmtOffset":0,"timeZoneId":"Europe/Dublin"},"lat":54.87472,"lng":-7.59833,"population":1157},{"id":2964999,"name":"Croom","timezone":{"dstOffset":1,"gmtOffset":0,"timeZoneId":"Europe/Dublin"},"lat":52.51944,"lng":-8.71778,"population":1157},{"id":2961349,"name":"Stradbally","timezone":{"dstOffset":1,"gmtOffset":0,"timeZoneId":"Europe/Dublin"},"lat":53.01556,"lng":-7.15278,"population":1154},{"id":2966857,"name":"Askeaton","timezone":{"dstOffset":1,"gmtOffset":0,"timeZoneId":"Europe/Dublin"},"lat":52.59972,"lng":-8.97556,"population":1149},{"id":2962376,"name":"Mullagh","timezone":{"dstOffset":1,"gmtOffset":0,"timeZoneId":"Europe/Dublin"},"lat":53.81306,"lng":-6.95139,"population":1137},{"id":2963208,"name":"Kiltamagh","timezone":{"dstOffset":1,"gmtOffset":0,"timeZoneId":"Europe/Dublin"},"lat":53.85,"lng":-9,"population":1127},{"id":3302076,"name":"Ballygerry","timezone":{"dstOffset":1,"gmtOffset":0,"timeZoneId":"Europe/Dublin"},"lat":52.24917,"lng":-6.35739,"population":1123},{"id":2964642,"name":"Dromiskin","timezone":{"dstOffset":1,"gmtOffset":0,"timeZoneId":"Europe/Dublin"},"lat":53.9275,"lng":-6.41139,"population":1115},{"id":2967076,"name":"Adare","timezone":{"dstOffset":1,"gmtOffset":0,"timeZoneId":"Europe/Dublin"},"lat":52.56194,"lng":-8.79556,"population":1106},{"id":7870969,"name":"Kentstown","timezone":{"dstOffset":1,"gmtOffset":0,"timeZoneId":"Europe/Dublin"},"lat":53.62754,"lng":-6.52674,"population":1099},{"id":3304313,"name":"Ballinroad","timezone":{"dstOffset":1,"gmtOffset":0,"timeZoneId":"Europe/Dublin"},"lat":52.51789,"lng":-6.40619,"population":1097},{"id":2965760,"name":"Carnew","timezone":{"dstOffset":1,"gmtOffset":0,"timeZoneId":"Europe/Dublin"},"lat":52.70806,"lng":-6.49444,"population":1091},{"id":2966208,"name":"Belmullet","timezone":{"dstOffset":1,"gmtOffset":0,"timeZoneId":"Europe/Dublin"},"lat":54.225,"lng":-9.99083,"population":1089},{"id":2966420,"name":"Ballyragget","timezone":{"dstOffset":1,"gmtOffset":0,"timeZoneId":"Europe/Dublin"},"lat":52.78889,"lng":-7.33028,"population":1089},{"id":7838899,"name":"Ballylinan","timezone":{"dstOffset":1,"gmtOffset":0,"timeZoneId":"Europe/Dublin"},"lat":52.94497,"lng":-7.04073,"population":1084},{"id":2962235,"name":"Newtown Cunningham","timezone":{"dstOffset":1,"gmtOffset":0,"timeZoneId":"Europe/Dublin"},"lat":54.99639,"lng":-7.51917,"population":1067},{"id":2960952,"name":"Whitegate","timezone":{"dstOffset":1,"gmtOffset":0,"timeZoneId":"Europe/Dublin"},"lat":51.83056,"lng":-8.22972,"population":1067},{"id":2964980,"name":"Crossmolina","timezone":{"dstOffset":1,"gmtOffset":0,"timeZoneId":"Europe/Dublin"},"lat":54.1,"lng":-9.31667,"population":1061},{"id":2966638,"name":"Ballyconnell","timezone":{"dstOffset":1,"gmtOffset":0,"timeZoneId":"Europe/Dublin"},"lat":54.11667,"lng":-7.58333,"population":1061},{"id":2963299,"name":"Killumney","timezone":{"dstOffset":1,"gmtOffset":0,"timeZoneId":"Europe/Dublin"},"lat":51.86667,"lng":-8.65,"population":1046},{"id":2965772,"name":"Carlingford","timezone":{"dstOffset":1,"gmtOffset":0,"timeZoneId":"Europe/Dublin"},"lat":54.04,"lng":-6.18833,"population":1045},{"id":2965573,"name":"Castlepollard","timezone":{"dstOffset":1,"gmtOffset":0,"timeZoneId":"Europe/Dublin"},"lat":53.66667,"lng":-7.3,"population":1042},{"id":2962054,"name":"Daingean","timezone":{"dstOffset":1,"gmtOffset":0,"timeZoneId":"Europe/Dublin"},"lat":53.29611,"lng":-7.28944,"population":1037},{"id":2965653,"name":"Castlebellingham","timezone":{"dstOffset":1,"gmtOffset":0,"timeZoneId":"Europe/Dublin"},"lat":53.90083,"lng":-6.39028,"population":1035},{"id":3315162,"name":"Kilmacanoge","timezone":{"dstOffset":1,"gmtOffset":0,"timeZoneId":"Europe/Dublin"},"lat":53.16722,"lng":-6.13361,"population":1028},{"id":2963902,"name":"Granard","timezone":{"dstOffset":1,"gmtOffset":0,"timeZoneId":"Europe/Dublin"},"lat":53.76667,"lng":-7.5,"population":1021},{"id":2963162,"name":"Kinlough","timezone":{"dstOffset":1,"gmtOffset":0,"timeZoneId":"Europe/Dublin"},"lat":54.45,"lng":-8.28333,"population":1018},{"id":2966842,"name":"Athgarvan","timezone":{"dstOffset":1,"gmtOffset":0,"timeZoneId":"Europe/Dublin"},"lat":53.15389,"lng":-6.805,"population":1016},{"id":2967061,"name":"Aghada","timezone":{"dstOffset":1,"gmtOffset":0,"timeZoneId":"Europe/Dublin"},"lat":51.83917,"lng":-8.21222,"population":1015},{"id":2963565,"name":"Johnstown","timezone":{"dstOffset":1,"gmtOffset":0,"timeZoneId":"Europe/Dublin"},"lat":53.23833,"lng":-6.62222,"population":1004},{"id":9409566,"name":"Farranacoush","timezone":{"dstOffset":1,"gmtOffset":0,"timeZoneId":"Europe/Dublin"},"lat":51.48304,"lng":-9.41228,"population":0}]