[{"id":587084,"name":"Baku","timezone":{"dstOffset":5,"gmtOffset":4,"timeZoneId":"Asia/Baku"},"lat":40.37767,"lng":49.89201,"population":1116513},{"id":586523,"name":"Ganja","timezone":{"dstOffset":5,"gmtOffset":4,"timeZoneId":"Asia/Baku"},"lat":40.68278,"lng":46.36056,"population":313300},{"id":584923,"name":"Sumqayit","timezone":{"dstOffset":5,"gmtOffset":4,"timeZoneId":"Asia/Baku"},"lat":40.58972,"lng":49.66861,"population":265150},{"id":147622,"name":"Lankaran","timezone":{"dstOffset":5,"gmtOffset":4,"timeZoneId":"Asia/Baku"},"lat":38.75428,"lng":48.85062,"population":240300},{"id":585514,"name":"Mingachevir","timezone":{"dstOffset":5,"gmtOffset":4,"timeZoneId":"Asia/Baku"},"lat":40.76395,"lng":47.05953,"population":95453},{"id":147288,"name":"Saatlı","timezone":{"dstOffset":5,"gmtOffset":4,"timeZoneId":"Asia/Baku"},"lat":39.93214,"lng":48.36892,"population":87000},{"id":585103,"name":"Qaraçuxur","timezone":{"dstOffset":5,"gmtOffset":4,"timeZoneId":"Asia/Baku"},"lat":40.39667,"lng":49.97361,"population":72989},{"id":148565,"name":"Şirvan","timezone":{"dstOffset":5,"gmtOffset":4,"timeZoneId":"Asia/Baku"},"lat":39.93778,"lng":48.929,"population":70220},{"id":824003,"name":"Bakıxanov","timezone":{"dstOffset":5,"gmtOffset":4,"timeZoneId":"Asia/Baku"},"lat":40.41894,"lng":49.96693,"population":66686},{"id":147429,"name":"Nakhichivan","timezone":{"dstOffset":5,"gmtOffset":4,"timeZoneId":"Asia/Baku"},"lat":39.20889,"lng":45.41222,"population":64754}]