[{"id":6618983,"name":"Zagreb - Centar","timezone":{"dstOffset":2,"gmtOffset":1,"timeZoneId":"Europe/Zagreb"},"lat":45.81313,"lng":15.97753,"population":800000},{"id":3186886,"name":"Zagreb","timezone":{"dstOffset":2,"gmtOffset":1,"timeZoneId":"Europe/Zagreb"},"lat":45.81444,"lng":15.97798,"population":698966},{"id":3190261,"name":"Split","timezone":{"dstOffset":2,"gmtOffset":1,"timeZoneId":"Europe/Zagreb"},"lat":43.50891,"lng":16.43915,"population":176314},{"id":3191648,"name":"Rijeka","timezone":{"dstOffset":2,"gmtOffset":1,"timeZoneId":"Europe/Zagreb"},"lat":45.34306,"lng":14.40917,"population":141172},{"id":3193935,"name":"Osijek","timezone":{"dstOffset":2,"gmtOffset":1,"timeZoneId":"Europe/Zagreb"},"lat":45.55111,"lng":18.69389,"population":88140},{"id":3186952,"name":"Zadar","timezone":{"dstOffset":2,"gmtOffset":1,"timeZoneId":"Europe/Zagreb"},"lat":44.11972,"lng":15.24222,"population":71258},{"id":3190586,"name":"Slavonski Brod","timezone":{"dstOffset":2,"gmtOffset":1,"timeZoneId":"Europe/Zagreb"},"lat":45.16028,"lng":18.01556,"population":60742},{"id":3192224,"name":"Pula","timezone":{"dstOffset":2,"gmtOffset":1,"timeZoneId":"Europe/Zagreb"},"lat":44.86833,"lng":13.84806,"population":59078},{"id":3190966,"name":"Sesvete","timezone":{"dstOffset":2,"gmtOffset":1,"timeZoneId":"Europe/Zagreb"},"lat":45.83111,"lng":16.11639,"population":52411},{"id":3198259,"name":"Karlovac","timezone":{"dstOffset":2,"gmtOffset":1,"timeZoneId":"Europe/Zagreb"},"lat":45.48722,"lng":15.54778,"population":48123}]