[{"id":2332459,"name":"Lagos","timezone":{"dstOffset":1,"gmtOffset":1,"timeZoneId":"Africa/Lagos"},"lat":6.45407,"lng":3.39467,"population":9000000},{"id":2335204,"name":"Kano","timezone":{"dstOffset":1,"gmtOffset":1,"timeZoneId":"Africa/Lagos"},"lat":12.00012,"lng":8.51672,"population":3626068},{"id":2339354,"name":"Ibadan","timezone":{"dstOffset":1,"gmtOffset":1,"timeZoneId":"Africa/Lagos"},"lat":7.37756,"lng":3.90591,"population":3565108},{"id":2335727,"name":"Kaduna","timezone":{"dstOffset":1,"gmtOffset":1,"timeZoneId":"Africa/Lagos"},"lat":10.52641,"lng":7.4388,"population":1582102},{"id":2324774,"name":"Port Harcourt","timezone":{"dstOffset":1,"gmtOffset":1,"timeZoneId":"Africa/Lagos"},"lat":4.77742,"lng":7.0134,"population":1148665},{"id":2347283,"name":"Benin City","timezone":{"dstOffset":1,"gmtOffset":1,"timeZoneId":"Africa/Lagos"},"lat":6.33815,"lng":5.62575,"population":1125058},{"id":2331447,"name":"Maiduguri","timezone":{"dstOffset":1,"gmtOffset":1,"timeZoneId":"Africa/Lagos"},"lat":11.84692,"lng":13.15712,"population":1112449},{"id":2317765,"name":"Zaria","timezone":{"dstOffset":1,"gmtOffset":1,"timeZoneId":"Africa/Lagos"},"lat":11.11128,"lng":7.7227,"population":975153},{"id":2353151,"name":"Aba","timezone":{"dstOffset":1,"gmtOffset":1,"timeZoneId":"Africa/Lagos"},"lat":5.10658,"lng":7.36667,"population":897560},{"id":2335953,"name":"Jos","timezone":{"dstOffset":1,"gmtOffset":1,"timeZoneId":"Africa/Lagos"},"lat":9.92849,"lng":8.89212,"population":816824}]